auditus/__init__.py
auditus/_modidx.py
auditus/core.py
auditus/transform.py
auditus-0.0.6.dist-info/LICENSE
auditus-0.0.6.dist-info/METADATA
auditus-0.0.6.dist-info/WHEEL
auditus-0.0.6.dist-info/entry_points.txt
auditus-0.0.6.dist-info/top_level.txt
auditus-0.0.6.dist-info/RECORD
