Metadata-Version: 2.1
Name: auditus
Version: 0.0.6
Summary: Simple Audio Embeddings
Home-page: https://github.com/CarloLepelaars/auditus
Author: Carlo Lepelaars
Author-email: info@carlolepelaars.nl
License: Apache Software License 2.0
Keywords: audio embeddings
Classifier: Development Status :: 4 - Beta
Classifier: Intended Audience :: Developers
Classifier: Natural Language :: English
Classifier: Programming Language :: Python :: 3.10
Classifier: Programming Language :: Python :: 3.11
Classifier: Programming Language :: Python :: 3.12
Classifier: Programming Language :: Python :: 3.13
Classifier: License :: OSI Approved :: Apache Software License
Requires-Python: >=3.10
License-File: LICENSE
Requires-Dist: fastcore
Requires-Dist: fasttransform
Requires-Dist: torch
Requires-Dist: transformers
Requires-Dist: tensorflow
Requires-Dist: numpy
Requires-Dist: soundfile
Requires-Dist: torch (<2.7,>=1.10)
Provides-Extra: dev
